Workbook
Name Office: 'Array Functions'!$B$2:$B$16
Name Sales01: 'Array Functions'!$D$2:$D$16
Name Sales02: 'Array Functions'!$E$2:$E$16

Sheet Formulas 101
A1: Date | B1: Phone Calls | C1: Leads | D1: Sales | E1: Leads per Call | F1: Sales per Call
A2: 42370 | B2: 146 | C2: 77 | D2: 18 | E2: =C2/$B$2 -> 0.52739726 | F2: =D2/$B$2 -> 0.12328767
A3: 42370 | B3: 169 | C3: 72 | D3: 15 | E3: =C3/$B$2 -> 0.49315068 | F3: =D3/$B$2 -> 0.10273973
A4: 42370 | B4: 199 | C4: 71 | D4: 19 | E4: =C4/$B$2 -> 0.48630137 | F4: =D4/$B$2 -> 0.13013699
A5: 42371 | B5: 281 | C5: 66 | D5: 10 | E5: =C5/$B$2 -> 0.45205479 | F5: =D5/$B$2 -> 0.068493151
A6: 42371 | B6: 266 | C6: 53 | D6: 19 | E6: =C6/$B$2 -> 0.3630137 | F6: =D6/$B$2 -> 0.13013699
A7: 42371 | B7: 277 | C7: 84 | D7: 15 | E7: =C7/$B$2 -> 0.57534247 | F7: =D7/$B$2 -> 0.10273973
A8: 42372 | B8: 145 | C8: 73 | D8: 15 | E8: =C8/$B$2 -> 0.5 | F8: =D8/$B$2 -> 0.10273973
A9: 42372 | B9: 227 | C9: 69 | D9: 12 | E9: =C9/$B$2 -> 0.47260274 | F9: =D9/$B$2 -> 0.082191781
A10: 42372 | B10: 180 | C10: 79 | D10: 16 | E10: =C10/$B$2 -> 0.54109589 | F10: =D10/$B$2 -> 0.10958904
A11: 42373 | B11: 0 | C11: 0 | D11: 0 | E11: =C11/$B$2 -> 0 | F11: =D11/$B$2 -> 0
A12: 42374 | B12: 242 | C12: 75 | D12: 10 | E12: =C12/$B$2 -> 0.51369863 | F12: =D12/$B$2 -> 0.068493151
A13: 42374 | B13: 215 | C13: 75 | D13: 16 | E13: =C13/$B$2 -> 0.51369863 | F13: =D13/$B$2 -> 0.10958904
... A26: 42377 | B26: 261 | C26: 90 | D26: 19 | E26: =C26/$B$2 -> 0.61643836 | F26: =D26/$B$2 -> 0.13013699

Sheet Logical Operators
A1: Student | B1: Gender | C1: Score | D1: Pass/Fail | E1: Letter | F1: Outlier | G1: Award
A2: Jill | B2: F | C2: 90 | D2: =IF(C2>=60,"PASS","FAIL") -> PASS | E2: =IF(C2>=90,"A",IF(AND(C2>80,C2<=89),"B",IF(AND(C2>70,C2<=79),"C",IF(AND(C2>=60,C2<=69),"D","F")))) -> A | F2: =IF(OR(C2<60,C2>90),"OUTLIER","AVG") -> AVG | G2: =IF(AND(B2="F",C2>95),"Female Achiever",IF(AND(B2="M",C2>95),"Male Achiever","None")) -> None
A3: Tom | B3: M | C3: 80 | D3: =IF(C3>=60,"PASS","FAIL") -> PASS | E3: =IF(C3>=90,"A",IF(AND(C3>80,C3<=89),"B",IF(AND(C3>70,C3<=79),"C",IF(AND(C3>=60,C3<=69),"D","F")))) -> F | F3: =IF(OR(C3<60,C3>90),"OUTLIER","AVG") -> AVG | G3: =IF(AND(B3="F",C3>95),"Female Achiever",IF(AND(B3="M",C3>95),"Male Achiever","None")) -> None
A4: Brittany | B4: F | C4: 96 | D4: =IF(C4>=60,"PASS","FAIL") -> PASS | E4: =IF(C4>=90,"A",IF(AND(C4>80,C4<=89),"B",IF(AND(C4>70,C4<=79),"C",IF(AND(C4>=60,C4<=69),"D","F")))) -> A | F4: =IF(OR(C4<60,C4>90),"OUTLIER","AVG") -> OUTLIER | G4: =IF(AND(B4="F",C4>95),"Female Achiever",IF(AND(B4="M",C4>95),"Male Achiever","None")) -> Female Achiever
A5: Alan | B5: M | C5: 72 | D5: =IF(C5>=60,"PASS","FAIL") -> PASS | E5: =IF(C5>=90,"A",IF(AND(C5>80,C5<=89),"B",IF(AND(C5>70,C5<=79),"C",IF(AND(C5>=60,C5<=69),"D","F")))) -> C | F5: =IF(OR(C5<60,C5>90),"OUTLIER","AVG") -> AVG | G5: =IF(AND(B5="F",C5>95),"Female Achiever",IF(AND(B5="M",C5>95),"Male Achiever","None")) -> None
A6: George | B6: M | C6: 69 | D6: =IF(C6>=60,"PASS","FAIL") -> PASS | E6: =IF(C6>=90,"A",IF(AND(C6>80,C6<=89),"B",IF(AND(C6>70,C6<=79),"C",IF(AND(C6>=60,C6<=69),"D","F")))) -> D | F6: =IF(OR(C6<60,C6>90),"OUTLIER","AVG") -> AVG | G6: =IF(AND(B6="F",C6>95),"Female Achiever",IF(AND(B6="M",C6>95),"Male Achiever","None")) -> None
A7: Sally | B7: F | C7: 52 | D7: =IF(C7>=60,"PASS","FAIL") -> FAIL | E7: =IF(C7>=90,"A",IF(AND(C7>80,C7<=89),"B",IF(AND(C7>70,C7<=79),"C",IF(AND(C7>=60,C7<=69),"D","F")))) -> F | F7: =IF(OR(C7<60,C7>90),"OUTLIER","AVG") -> OUTLIER | G7: =IF(AND(B7="F",C7>95),"Female Achiever",IF(AND(B7="M",C7>95),"Male Achiever","None")) -> None
A8: Chris | B8: M | C8: 99 | D8: =IF(C8>=60,"PASS","FAIL") -> PASS | E8: =IF(C8>=90,"A",IF(AND(C8>80,C8<=89),"B",IF(AND(C8>70,C8<=79),"C",IF(AND(C8>=60,C8<=69),"D","F")))) -> A | F8: =IF(OR(C8<60,C8>90),"OUTLIER","AVG") -> OUTLIER | G8: =IF(AND(B8="F",C8>95),"Female Achiever",IF(AND(B8="M",C8>95),"Male Achiever","None")) -> Male Achiever
A9: Jamie | B9: F | C9: 82 | D9: =IF(C9>=60,"PASS","FAIL") -> PASS | E9: =IF(C9>=90,"A",IF(AND(C9>80,C9<=89),"B",IF(AND(C9>70,C9<=79),"C",IF(AND(C9>=60,C9<=69),"D","F")))) -> B | F9: =IF(OR(C9<60,C9>90),"OUTLIER","AVG") -> AVG | G9: =IF(AND(B9="F",C9>95),"Female Achiever",IF(AND(B9="M",C9>95),"Male Achiever","None")) -> None
A10: Valorie | B10: F | C10: 67 | D10: =IF(C10>=60,"PASS","FAIL") -> PASS | E10: =IF(C10>=90,"A",IF(AND(C10>80,C10<=89),"B",IF(AND(C10>70,C10<=79),"C",IF(AND(C10>=60,C10<=69),"D","F")))) -> D | F10: =IF(OR(C10<60,C10>90),"OUTLIER","AVG") -> AVG | G10: =IF(AND(B10="F",C10>95),"Female Achiever",IF(AND(B10="M",C10>95),"Male Achiever","None")) -> None
A11: Steve | B11: M | C11: 90 | D11: =IF(C11>=60,"PASS","FAIL") -> PASS | E11: =IF(C11>=90,"A",IF(AND(C11>80,C11<=89),"B",IF(AND(C11>70,C11<=79),"C",IF(AND(C11>=60,C11<=69),"D","F")))) -> A | F11: =IF(OR(C11<60,C11>90),"OUTLIER","AVG") -> AVG | G11: =IF(AND(B11="F",C11>95),"Female Achiever",IF(AND(B11="M",C11>95),"Male Achiever","None")) -> None
A12: Jake | B12: M | C12: 83 | D12: =IF(C12>=60,"PASS","FAIL") -> PASS | E12: =IF(C12>=90,"A",IF(AND(C12>80,C12<=89),"B",IF(AND(C12>70,C12<=79),"C",IF(AND(C12>=60,C12<=69),"D","F")))) -> B | F12: =IF(OR(C12<60,C12>90),"OUTLIER","AVG") -> AVG | G12: =IF(AND(B12="F",C12>95),"Female Achiever",IF(AND(B12="M",C12>95),"Male Achiever","None")) -> None
A13: Lori | B13: F | C13: 89 | D13: =IF(C13>=60,"PASS","FAIL") -> PASS | E13: =IF(C13>=90,"A",IF(AND(C13>80,C13<=89),"B",IF(AND(C13>70,C13<=79),"C",IF(AND(C13>=60,C13<=69),"D","F")))) -> B | F13: =IF(OR(C13<60,C13>90),"OUTLIER","AVG") -> AVG | G13: =IF(AND(B13="F",C13>95),"Female Achiever",IF(AND(B13="M",C13>95),"Male Achiever","None")) -> None
... A16: Tim | B16: M | C16: 59 | D16: =IF(C16>=60,"PASS","FAIL") -> FAIL | E16: =IF(C16>=90,"A",IF(AND(C16>80,C16<=89),"B",IF(AND(C16>70,C16<=79),"C",IF(AND(C16>=60,C16<=69),"D","F")))) -> F | F16: =IF(OR(C16<60,C16>90),"OUTLIER","AVG") -> OUTLIER | G16: =IF(AND(B16="F",C16>95),"Female Achiever",IF(AND(B16="M",C16>95),"Male Achiever","None")) -> None

Sheet Stats Functions
A1: Product Category | B1: Product ID | C1: Store Location | D1: Sales | E1: Revenue | M1: Apparel & Accessories
A2: Apparel & Accessories | B2: 402850 | C2: Boston | D2: 17 | E2: 2499 | G2: Product Category: | H2: Apparel & Accessories | M2: Consumer Electronics
A3: Apparel & Accessories | B3: 436987 | C3: Boston | D3: 98 | E3: 784 | M3: Health & Beauty
A4: Apparel & Accessories | B4: 764613 | C4: Boston | D4: 51 | E4: 6732 | H4: Total Sales | M4: Food & Beverage
A5: Apparel & Accessories | B5: 243484 | C5: Chicago | D5: 32 | E5: 3072 | H5: =SUMIF(A:A,$H$2,D:D) -> 620
A6: Apparel & Accessories | B6: 522010 | C6: Chicago | D6: 171 | E6: 25650
A7: Apparel & Accessories | B7: 346155 | C7: Chicago | D7: 51 | E7: 3876 | H7: Total Sales | I7: Total Revenue | J7: Number of Product IDs
A8: Apparel & Accessories | B8: 181763 | C8: Chicago | D8: 118 | E8: 10030 | G8: Boston | H8: =SUMIFS($D:$D,A:A,$H$2,$C:$C,G8) -> 166 | I8: =SUMIFS($E:$E,$A:$A,$H$2,$C:$C,G8) -> 10015 | J8: =COUNTIFS($A:$A,$H$2,$C:$C,G8) -> 3
A9: Apparel & Accessories | B9: 410456 | C9: New York | D9: 52 | E9: 2340 | G9: Chicago | H9: =SUMIFS($D:$D,A:A,$H$2,$C:$C,G9) -> 372 | I9: =SUMIFS($E:$E,$A:$A,$H$2,$C:$C,G9) -> 42628 | J9: =COUNTIFS($A:$A,$H$2,$C:$C,G9) -> 4
A10: Apparel & Accessories | B10: 454175 | C10: New York | D10: 30 | E10: 3960 | G10: New York | H10: =SUMIFS($D:$D,A:A,$H$2,$C:$C,G10) -> 82 | I10: =SUMIFS($E:$E,$A:$A,$H$2,$C:$C,G10) -> 6300 | J10: =COUNTIFS($A:$A,$H$2,$C:$C,G10) -> 2
A11: Consumer Electronics | B11: 426853 | C11: Boston | D11: 114 | E11: 4446
A12: Consumer Electronics | B12: 815098 | C12: Boston | D12: 49 | E12: 5537
A13: Consumer Electronics | B13: 209537 | C13: Boston | D13: 155 | E13: 21390
A14: Consumer Electronics | B14: 765870 | C14: Boston | D14: 101 | E14: 3535
A15: Consumer Electronics | B15: 747542 | C15: Chicago | D15: 149 | E15: 11324
A16: Consumer Electronics | B16: 177975 | C16: Chicago | D16: 119 | E16: 17850
A17: Consumer Electronics | B17: 840614 | C17: New York | D17: 97 | E17: 3298
A18: Consumer Electronics | B18: 271572 | C18: New York | D18: 127 | E18: 17907
A19: Consumer Electronics | B19: 367240 | C19: New York | D19: 104 | E19: 12584
A20: Consumer Electronics | B20: 791819 | C20: New York | D20: 91 | E20: 9282
A21: Health & Beauty | B21: 185858 | C21: Boston | D21: 51 | E21: 765
A22: Health & Beauty | B22: 501837 | C22: Boston | D22: 142 | E22: 14484
... A70: Food & Beverage | B70: 465336 | C70: New York | D70: 196 | E70: 20776

Sheet Lookup Functions
A1: Key | B1: State | C1: Year | D1: Total Population | E1: Student Population | F1: State Abbreviation | G1: Per Capita Income
A2: =B2&C2 -> Alabama2001 | B2: Alabama | C2: 2001 | D2: 4447100 | E2: 177884 | F2: =VLOOKUP(B2,'State Abbreviations'!$A$2:$B$52,2,0) -> AL | G2: =IFERROR(VLOOKUP(A2,'State Income (2001-2004)'!$A:$D,4,0),"NO INCOME DATA") -> 24477
A3: =B3&C3 -> Alaska2001 | B3: Alaska | C3: 2001 | D3: 626932 | E3: 12538.64 | F3: =VLOOKUP(B3,'State Abbreviations'!$A$2:$B$52,2,0) -> AK | G3: =IFERROR(VLOOKUP(A3,'State Income (2001-2004)'!$A:$D,4,0),"NO INCOME DATA") -> 31027
A4: =B4&C4 -> Arizona2001 | B4: Arizona | C4: 2001 | D4: 5130632 | E4: 102612.64 | F4: =VLOOKUP(B4,'State Abbreviations'!$A$2:$B$52,2,0) -> AZ | G4: =IFERROR(VLOOKUP(A4,'State Income (2001-2004)'!$A:$D,4,0),"NO INCOME DATA") -> 25878
A5: =B5&C5 -> Arkansas2001 | B5: Arkansas | C5: 2001 | D5: 2673400 | E5: 53468 | F5: =VLOOKUP(B5,'State Abbreviations'!$A$2:$B$52,2,0) -> AR | G5: =IFERROR(VLOOKUP(A5,'State Income (2001-2004)'!$A:$D,4,0),"NO INCOME DATA") -> 22750
A6: =B6&C6 -> California2001 | B6: California | C6: 2001 | D6: 33871648 | E6: 1016149.4 | F6: =VLOOKUP(B6,'State Abbreviations'!$A$2:$B$52,2,0) -> CA | G6: =IFERROR(VLOOKUP(A6,'State Income (2001-2004)'!$A:$D,4,0),"NO INCOME DATA") -> 32655
A7: =B7&C7 -> Colorado2001 | B7: Colorado | C7: 2001 | D7: 4301261 | E7: 172050.44 | F7: =VLOOKUP(B7,'State Abbreviations'!$A$2:$B$52,2,0) -> CO | G7: =IFERROR(VLOOKUP(A7,'State Income (2001-2004)'!$A:$D,4,0),"NO INCOME DATA") -> 33455
A8: =B8&C8 -> Connecticut2001 | B8: Connecticut | C8: 2001 | D8: 3405565 | E8: 102166.95 | F8: =VLOOKUP(B8,'State Abbreviations'!$A$2:$B$52,2,0) -> CT | G8: =IFERROR(VLOOKUP(A8,'State Income (2001-2004)'!$A:$D,4,0),"NO INCOME DATA") -> NO INCOME DATA
A9: =B9&C9 -> D.C.2001 | B9: D.C. | C9: 2001 | D9: 783600 | E9: 23508 | F9: =VLOOKUP(B9,'State Abbreviations'!$A$2:$B$52,2,0) -> DC | G9: =IFERROR(VLOOKUP(A9,'State Income (2001-2004)'!$A:$D,4,0),"NO INCOME DATA") -> 32166
A10: =B10&C10 -> Delaware2001 | B10: Delaware | C10: 2001 | D10: 572059 | E10: 17161.77 | F10: =VLOOKUP(B10,'State Abbreviations'!$A$2:$B$52,2,0) -> DE | G10: =IFERROR(VLOOKUP(A10,'State Income (2001-2004)'!$A:$D,4,0),"NO INCOME DATA") -> 40539
A11: =B11&C11 -> Florida2001 | B11: Florida | C11: 2001 | D11: 15982378 | E11: 319647.56 | F11: =VLOOKUP(B11,'State Abbreviations'!$A$2:$B$52,2,0) -> FL | G11: =IFERROR(VLOOKUP(A11,'State Income (2001-2004)'!$A:$D,4,0),"NO INCOME DATA") -> 29048
A12: =B12&C12 -> Georgia2001 | B12: Georgia | C12: 2001 | D12: 8186453 | E12: 245593.59 | F12: =VLOOKUP(B12,'State Abbreviations'!$A$2:$B$52,2,0) -> GA | G12: =IFERROR(VLOOKUP(A12,'State Income (2001-2004)'!$A:$D,4,0),"NO INCOME DATA") -> 28523
A13: =B13&C13 -> Hawaii2001 | B13: Hawaii | C13: 2001 | D13: 1211537 | E13: 48461.48 | F13: =VLOOKUP(B13,'State Abbreviations'!$A$2:$B$52,2,0) -> HI | G13: =IFERROR(VLOOKUP(A13,'State Income (2001-2004)'!$A:$D,4,0),"NO INCOME DATA") -> 29034
... A205: =B205&C205 -> Wyoming2004 | B205: Wyoming | C205: 2004 | D205: 576412 | E205: 11528.24 | F205: =VLOOKUP(B205,'State Abbreviations'!$A$2:$B$52,2,0) -> WY | G205: =IFERROR(VLOOKUP(A205,'State Income (2001-2004)'!$A:$D,4,0),"NO INCOME DATA") -> 36778

Sheet State Abbreviations
A1: State | B1: State Abbreviation
A2: Alabama | B2: AL
A3: Alaska | B3: AK
A4: Arizona | B4: AZ
A5: Arkansas | B5: AR
A6: California | B6: CA
A7: Colorado | B7: CO
A8: Connecticut | B8: CT
A9: D.C. | B9: DC
A10: Delaware | B10: DE
A11: Florida | B11: FL
A12: Georgia | B12: GA
... A52: Wyoming | B52: WY

Sheet State Income (2001-2004)
A1: Key | B1: State | C1: Year | D1: Per Capita Income
A2: =CONCATENATE(B2,C2) -> Alabama2001 | B2: Alabama | C2: 2001 | D2: 24477
A3: =CONCATENATE(B3,C3) -> Alaska2001 | B3: Alaska | C3: 2001 | D3: 31027
A4: =CONCATENATE(B4,C4) -> Arizona2001 | B4: Arizona | C4: 2001 | D4: 25878
A5: =CONCATENATE(B5,C5) -> Arkansas2001 | B5: Arkansas | C5: 2001 | D5: 22750
A6: =CONCATENATE(B6,C6) -> California2001 | B6: California | C6: 2001 | D6: 32655
A7: =CONCATENATE(B7,C7) -> Colorado2001 | B7: Colorado | C7: 2001 | D7: 33455
A8: =CONCATENATE(B8,C8) -> D.C.2001 | B8: D.C. | C8: 2001 | D8: 32166
A9: =CONCATENATE(B9,C9) -> Delaware2001 | B9: Delaware | C9: 2001 | D9: 40539
A10: =CONCATENATE(B10,C10) -> Florida2001 | B10: Florida | C10: 2001 | D10: 29048
A11: =CONCATENATE(B11,C11) -> Georgia2001 | B11: Georgia | C11: 2001 | D11: 28523
A12: =CONCATENATE(B12,C12) -> Hawaii2001 | B12: Hawaii | C12: 2001 | D12: 29034
A13: =CONCATENATE(B13,C13) -> Idaho2001 | B13: Idaho | C13: 2001 | D13: 24506
... A190: =CONCATENATE(B190,C190) -> Wyoming2004 | B190: Wyoming | C190: 2004 | D190: 36778

Sheet INDEX & MATCH
A1: Year | B1: Impressions | C1: Clicks | D1: Transactions
A2: 2000 | B2: 36487 | C2: 7079 | D2: 38 | F2: Year: | G2: 2000
A3: 2001 | B3: 35832 | C3: 9023 | D3: 42 | F3: Metric: | G3: Impressions
A4: 2002 | B4: 31170 | C4: 7100 | D4: 40
A5: 2003 | B5: 27782 | C5: 8586 | D5: 46 | F5: TOTAL: | G5: =INDEX($A$1:$D$18,MATCH($G$2,$A$1:$A$18,0),MATCH($G$3,$A$1:$D$1,0)) -> 36487
A6: 2004 | B6: 32952 | C6: 7726 | D6: 46
A7: 2005 | B7: 26275 | C7: 9759 | D7: 25
A8: 2006 | B8: 29767 | C8: 9325 | D8: 30
A9: 2007 | B9: 32118 | C9: 9154 | D9: 38
A10: 2008 | B10: 33634 | C10: 8377 | D10: 41
A11: 2009 | B11: 31634 | C11: 8069 | D11: 40
A12: 2010 | B12: 39392 | C12: 7266 | D12: 30
A13: 2011 | B13: 30892 | C13: 8895 | D13: 27
A14: 2012 | B14: 31450 | C14: 9986 | D14: 32
A15: 2013 | B15: 32382 | C15: 8232 | D15: 33
A16: 2014 | B16: 31536 | C16: 9653 | D16: 32
A17: 2015 | B17: 26286 | C17: 8467 | D17: 48
A18: 2016 | B18: 25347 | C18: 7541 | D18: 25

Sheet OFFSET & COUNTA
A1: Date | B1: Value
A2: 42370 | B2: 50 | C2: # of Dates in Column A: | D2: =COUNTA(A:A)-1 -> 20
A3: 42371 | B3: 11
A4: 42372 | B4: 79 | C4: Latest Date in Column A: | D4: =OFFSET(A:A,20,,1,1) -> 42389
A5: 42373 | B5: 51
A6: 42374 | B6: 87 | C6: Last Value in Column B: | D6: =OFFSET(A1,COUNTA(A:A)-1,1,1,1) -> 26
A7: 42375 | B7: 10
A8: 42376 | B8: 13 | C8: Sum of all Values in Column B: | D8: =SUM(OFFSET(B1,0,0,COUNTA(B:B),1)) -> 997
A9: 42377 | B9: 53
A10: 42378 | B10: 48 | C10: Sum of Values through previous day: | D10: =SUM(OFFSET(B1,0,0,COUNTA(B:B)-1,1)) -> 971
A11: 42379 | B11: 48
A12: 42380 | B12: 34
A13: 42381 | B13: 68
A14: 42382 | B14: 50
A15: 42383 | B15: 16
A16: 42384 | B16: 61
A17: 42385 | B17: 41
A18: 42386 | B18: 99
A19: 42387 | B19: 68
A20: 42388 | B20: 84
A21: 42389 | B21: 26

Sheet Text Functions
A1: Product Key | B1: Product ID (v1) | C1: Product ID (v2) | D1: Product Category | E1: Product Size (v1) | F1: Product Size (v2) | G1: New Key | H1: City
A2: 133462-AA-BOS_SMALL | B2: =LEFT(A2,6) -> 133462 | C2: =LEFT(A2,SEARCH("-",A2)-1) -> 133462 | D2: =MID(A2,SEARCH("-",A2)+1,2) -> AA | E2: =IF(ISNUMBER(SEARCH("small",A2)),"SMALL",IF(ISNUMBER(SEARCH("Medium",A2)),"MEDIUM",IF(ISNUMBER(SEARCH("large",A2)),"LARGE","XL"))) -> SMALL | F2: =RIGHT(A2,LEN(A2)-SEARCH("_",A2)) -> SMALL | G2: =SUBSTITUTE(A2,"-","|",2) -> 133462-AA|BOS_SMALL | H2: =MID(G2,SEARCH("|",G2)+1,3) -> BOS
A3: 191768-AC-NYC_MEDIUM | B3: =LEFT(A3,6) -> 191768 | C3: =LEFT(A3,SEARCH("-",A3)-1) -> 191768 | D3: =MID(A3,SEARCH("-",A3)+1,2) -> AC | E3: =IF(ISNUMBER(SEARCH("small",A3)),"SMALL",IF(ISNUMBER(SEARCH("Medium",A3)),"MEDIUM",IF(ISNUMBER(SEARCH("large",A3)),"LARGE","XL"))) -> MEDIUM | F3: =RIGHT(A3,LEN(A3)-SEARCH("_",A3)) -> MEDIUM | G3: =SUBSTITUTE(A3,"-","|",2) -> 191768-AC|NYC_MEDIUM | H3: =MID(G3,SEARCH("|",G3)+1,3) -> NYC
A4: 157263-BB-BOS_XL | B4: =LEFT(A4,6) -> 157263 | C4: =LEFT(A4,SEARCH("-",A4)-1) -> 157263 | D4: =MID(A4,SEARCH("-",A4)+1,2) -> BB | E4: =IF(ISNUMBER(SEARCH("small",A4)),"SMALL",IF(ISNUMBER(SEARCH("Medium",A4)),"MEDIUM",IF(ISNUMBER(SEARCH("large",A4)),"LARGE","XL"))) -> XL | F4: =RIGHT(A4,LEN(A4)-SEARCH("_",A4)) -> XL | G4: =SUBSTITUTE(A4,"-","|",2) -> 157263-BB|BOS_XL | H4: =MID(G4,SEARCH("|",G4)+1,3) -> BOS
A5: 1734372-AA-CHI_SMALL | B5: =LEFT(A5,6) -> 173437 | C5: =LEFT(A5,SEARCH("-",A5)-1) -> 1734372 | D5: =MID(A5,SEARCH("-",A5)+1,2) -> AA | E5: =IF(ISNUMBER(SEARCH("small",A5)),"SMALL",IF(ISNUMBER(SEARCH("Medium",A5)),"MEDIUM",IF(ISNUMBER(SEARCH("large",A5)),"LARGE","XL"))) -> SMALL | F5: =RIGHT(A5,LEN(A5)-SEARCH("_",A5)) -> SMALL | G5: =SUBSTITUTE(A5,"-","|",2) -> 1734372-AA|CHI_SMALL | H5: =MID(G5,SEARCH("|",G5)+1,3) -> CHI
A6: 135351-BC-NYC_XL | B6: =LEFT(A6,6) -> 135351 | C6: =LEFT(A6,SEARCH("-",A6)-1) -> 135351 | D6: =MID(A6,SEARCH("-",A6)+1,2) -> BC | E6: =IF(ISNUMBER(SEARCH("small",A6)),"SMALL",IF(ISNUMBER(SEARCH("Medium",A6)),"MEDIUM",IF(ISNUMBER(SEARCH("large",A6)),"LARGE","XL"))) -> XL | F6: =RIGHT(A6,LEN(A6)-SEARCH("_",A6)) -> XL | G6: =SUBSTITUTE(A6,"-","|",2) -> 135351-BC|NYC_XL | H6: =MID(G6,SEARCH("|",G6)+1,3) -> NYC
A7: 14330305-AC-BOS_LARGE | B7: =LEFT(A7,6) -> 143303 | C7: =LEFT(A7,SEARCH("-",A7)-1) -> 14330305 | D7: =MID(A7,SEARCH("-",A7)+1,2) -> AC | E7: =IF(ISNUMBER(SEARCH("small",A7)),"SMALL",IF(ISNUMBER(SEARCH("Medium",A7)),"MEDIUM",IF(ISNUMBER(SEARCH("large",A7)),"LARGE","XL"))) -> LARGE | F7: =RIGHT(A7,LEN(A7)-SEARCH("_",A7)) -> LARGE | G7: =SUBSTITUTE(A7,"-","|",2) -> 14330305-AC|BOS_LARGE | H7: =MID(G7,SEARCH("|",G7)+1,3) -> BOS
A8: 177772-BB-NYC_MEDIUM | B8: =LEFT(A8,6) -> 177772 | C8: =LEFT(A8,SEARCH("-",A8)-1) -> 177772 | D8: =MID(A8,SEARCH("-",A8)+1,2) -> BB | E8: =IF(ISNUMBER(SEARCH("small",A8)),"SMALL",IF(ISNUMBER(SEARCH("Medium",A8)),"MEDIUM",IF(ISNUMBER(SEARCH("large",A8)),"LARGE","XL"))) -> MEDIUM | F8: =RIGHT(A8,LEN(A8)-SEARCH("_",A8)) -> MEDIUM | G8: =SUBSTITUTE(A8,"-","|",2) -> 177772-BB|NYC_MEDIUM | H8: =MID(G8,SEARCH("|",G8)+1,3) -> NYC
A9: 87192837-AB-CHI_XL | B9: =LEFT(A9,6) -> 871928 | C9: =LEFT(A9,SEARCH("-",A9)-1) -> 87192837 | D9: =MID(A9,SEARCH("-",A9)+1,2) -> AB | E9: =IF(ISNUMBER(SEARCH("small",A9)),"SMALL",IF(ISNUMBER(SEARCH("Medium",A9)),"MEDIUM",IF(ISNUMBER(SEARCH("large",A9)),"LARGE","XL"))) -> XL | F9: =RIGHT(A9,LEN(A9)-SEARCH("_",A9)) -> XL | G9: =SUBSTITUTE(A9,"-","|",2) -> 87192837-AB|CHI_XL | H9: =MID(G9,SEARCH("|",G9)+1,3) -> CHI
A10: 161266-BB-CHI_SMALL | B10: =LEFT(A10,6) -> 161266 | C10: =LEFT(A10,SEARCH("-",A10)-1) -> 161266 | D10: =MID(A10,SEARCH("-",A10)+1,2) -> BB | E10: =IF(ISNUMBER(SEARCH("small",A10)),"SMALL",IF(ISNUMBER(SEARCH("Medium",A10)),"MEDIUM",IF(ISNUMBER(SEARCH("large",A10)),"LARGE","XL"))) -> SMALL | F10: =RIGHT(A10,LEN(A10)-SEARCH("_",A10)) -> SMALL | G10: =SUBSTITUTE(A10,"-","|",2) -> 161266-BB|CHI_SMALL | H10: =MID(G10,SEARCH("|",G10)+1,3) -> CHI
A11: 122892-AA-NYC_MEDIUM | B11: =LEFT(A11,6) -> 122892 | C11: =LEFT(A11,SEARCH("-",A11)-1) -> 122892 | D11: =MID(A11,SEARCH("-",A11)+1,2) -> AA | E11: =IF(ISNUMBER(SEARCH("small",A11)),"SMALL",IF(ISNUMBER(SEARCH("Medium",A11)),"MEDIUM",IF(ISNUMBER(SEARCH("large",A11)),"LARGE","XL"))) -> MEDIUM | F11: =RIGHT(A11,LEN(A11)-SEARCH("_",A11)) -> MEDIUM | G11: =SUBSTITUTE(A11,"-","|",2) -> 122892-AA|NYC_MEDIUM | H11: =MID(G11,SEARCH("|",G11)+1,3) -> NYC
A12: 128919-AC-CHI_XL | B12: =LEFT(A12,6) -> 128919 | C12: =LEFT(A12,SEARCH("-",A12)-1) -> 128919 | D12: =MID(A12,SEARCH("-",A12)+1,2) -> AC | E12: =IF(ISNUMBER(SEARCH("small",A12)),"SMALL",IF(ISNUMBER(SEARCH("Medium",A12)),"MEDIUM",IF(ISNUMBER(SEARCH("large",A12)),"LARGE","XL"))) -> XL | F12: =RIGHT(A12,LEN(A12)-SEARCH("_",A12)) -> XL | G12: =SUBSTITUTE(A12,"-","|",2) -> 128919-AC|CHI_XL | H12: =MID(G12,SEARCH("|",G12)+1,3) -> CHI
A13: 191999-BB-BOS_LARGE | B13: =LEFT(A13,6) -> 191999 | C13: =LEFT(A13,SEARCH("-",A13)-1) -> 191999 | D13: =MID(A13,SEARCH("-",A13)+1,2) -> BB | E13: =IF(ISNUMBER(SEARCH("small",A13)),"SMALL",IF(ISNUMBER(SEARCH("Medium",A13)),"MEDIUM",IF(ISNUMBER(SEARCH("large",A13)),"LARGE","XL"))) -> LARGE | F13: =RIGHT(A13,LEN(A13)-SEARCH("_",A13)) -> LARGE | G13: =SUBSTITUTE(A13,"-","|",2) -> 191999-BB|BOS_LARGE | H13: =MID(G13,SEARCH("|",G13)+1,3) -> BOS
... A15: 112283-AB-BOS_MEDIUM | B15: =LEFT(A15,6) -> 112283 | C15: =LEFT(A15,SEARCH("-",A15)-1) -> 112283 | D15: =MID(A15,SEARCH("-",A15)+1,2) -> AB | E15: =IF(ISNUMBER(SEARCH("small",A15)),"SMALL",IF(ISNUMBER(SEARCH("Medium",A15)),"MEDIUM",IF(ISNUMBER(SEARCH("large",A15)),"LARGE","XL"))) -> MEDIUM | F15: =RIGHT(A15,LEN(A15)-SEARCH("_",A15)) -> MEDIUM | G15: =SUBSTITUTE(A15,"-","|",2) -> 112283-AB|BOS_MEDIUM | H15: =MID(G15,SEARCH("|",G15)+1,3) -> BOS

Sheet Date & Time Functions
B2: Start Date: | C2: 42005
B3: TODAY: | C3: =TODAY() -> 46017
B4: NOW: | C4: =NOW() -> 46017.285
B6: YEAR | C6: MONTH | D6: DAY | E6: HOUR | F6: MINUTE | G6: SECOND
B7: =YEAR(C3) -> 2025 | C7: =MONTH(C3) -> 12 | D7: =DAY(C3) -> 26 | E7: =HOUR(C4) -> 6 | F7: =MINUTE(C4) -> 49 | G7: =SECOND(C4) -> 43
B9: WEEKDAY: | C9: =WEEKDAY(C3) -> 6
B11: WORKDAY: | C11: =WORKDAY(C3,50) -> 46087
B12: NETWORKDAY: | C12: =NETWORKDAYS(C2,C3) -> 2867
B14: LAST DAY OF MONTH: | C14: =EOMONTH(C3,C7+1) -> 46418
B15: FIRST DAY OF MONTH: | C15: =EOMONTH(C3,-1)+1 -> 45992
B16: FIRST DAY OF YEAR: | C16: =EOMONTH(C3,(-1*C7))+1 -> 45658
B18: Date
B19: 42005
B20: 42370
B21: 42736
B22: 43101
B23: 43466
B24: 43831
B25: 44197
B26: 44562
B27: 44927
B28: 45292
B29: 45658
B30: 46023

Sheet Formula Formatting
A1: Date | B1: Revenue | C1: Revenue Change | D1: Cost | E1: Profit | F1: Top Product Category | G1: Profit Margin
A2: 41640 | B2: 1099 | C2: 275 | D2: 643 | E2: =B2-D2 -> 456 | F2: Apparel | G2: =E2/B2 -> 0.41492266
A3: 41671 | B3: 1204 | C3: =B3-B2 -> 105 | D3: 720 | E3: 211 | F3: Electronics | G3: =E3/B3 -> 0.17524917
A4: 41699 | B4: 1944 | C4: =B4-B3 -> 740 | D4: 964 | E4: =B4-D4 -> 980 | F4: Kids | G4: =E4/B4 -> 0.50411523
A5: 41730 | B5: 1743 | C5: =B5-B4 -> -201 | D5: 830 | E5: =B5-D5 -> 913 | F5: Apparel | G5: =E5/B5 -> 0.52380952
A6: 41760 | B6: 1609 | C6: =B6-B5 -> -134 | D6: 910 | E6: =B6-D6 -> 699 | F6: Electronics | G6: =E6/B6 -> 0.43443132
A7: 41791 | B7: 1494 | C7: =B7-B6 -> -115 | D7: 909 | E7: =B7-D7 -> 585 | F7: Apparel | G7: =E7/B7 -> 0.39156627
A8: 41821 | B8: 1959 | C8: =B8-B7 -> 465 | D8: 830 | E8: =B8-D8 -> 1129 | F8: Electronics | G8: =E8/B8 -> 0.57631445
A9: 41852 | B9: 1868 | C9: =B9-B8 -> -91 | D9: 906 | E9: =B9-D9 -> 962 | F9: Apparel | G9: =E9/B9 -> 0.51498929
A10: 41883 | B10: 1162 | C10: =B10-B9 -> -706 | D10: 606 | E10: =B10-D10 -> 556 | F10: Kids | G10: =E10/B10 -> 0.47848537
A11: 41913 | B11: 1424 | C11: =B11-B10 -> 262 | D11: 943 | E11: =B11-D11 -> 481 | F11: Kids | G11: =E11/B11 -> 0.3377809
A12: 41944 | B12: 1232 | C12: =B12-B11 -> -192 | D12: 801 | E12: =B12-D12 -> 431 | F12: Electronics | G12: =E12/B12 -> 0.34983766
A13: 41974 | B13: 1738 | C13: =B13-B12 -> 506 | D13: 786 | E13: =B13-D13 -> 952 | F13: Apparel | G13: =E13/B13 -> 0.54775604
A14: 42005 | B14: 1435 | C14: =B14-B13 -> -303 | D14: 575 | E14: =B14-D14 -> 860 | F14: Electronics | G14: =E14/B14 -> 0.59930314
A15: 42036 | B15: 1865 | C15: =B15-B14 -> 430 | D15: 754 | E15: =B15-D15 -> 1111 | F15: Electronics | G15: =E15/B15 -> 0.59571046
... A19: 42156 | B19: 1356 | C19: =B19-B18 -> -627 | D19: 577 | E19: =B19-D19 -> 779 | F19: Kids | G19: =E19/B19 -> 0.57448378
A20: 42186 | B20: 1874 | C20: =B20-B19 -> 518 | D20: 865 | E20: 883 | F20: Electronics | G20: =E20/B20 -> 0.47118463
A21: 42217 | B21: 1479 | C21: =B21-B20 -> -395 | D21: 588 | E21: =B21-D21 -> 891 | F21: Apparel | G21: =E21/B21 -> 0.60243408
A22: 42248 | B22: 1943 | C22: =B22-B21 -> 464 | D22: 785 | E22: 712 | F22: Electronics | G22: =E22/B22 -> 0.36644364
A23: 42278 | B23: 1444 | C23: =B23-B22 -> -499 | D23: 657 | E23: =B23-D23 -> 787 | F23: Apparel | G23: =E23/B23 -> 0.54501385
A24: 42309 | B24: 1493 | C24: =B24-B23 -> 49 | D24: 880 | E24: =B24-D24 -> 613 | F24: Kids | G24: =E24/B24 -> 0.41058272
A25: 42339 | B25: 1738 | C25: =B25-B24 -> 245 | D25: 580 | E25: =B25-D25 -> 1158 | F25: Electronics | G25: =E25/B25 -> 0.66628308

Sheet Array Functions
A1: Employee | B1: Office | C1: Department | D1: 2015 Sales | E1: 2016 Sales
A2: Kathy | B2: BOS | C2: Electronics | D2: 18270 | E2: 22873 | G2: Max 2016 Sales in NYC office: | H2: {=MAX(IF(Office="NYC",Sales02))} -> 25897
A3: John | B3: BOS | C3: Electronics | D3: 20510 | E3: 21279
A4: Mindy | B4: BOS | C4: Apparel | D4: 15972 | E4: 13096 | G4: Max 2016 Sales in NYC office, Electronics only: | H4: {=MAX(IF((Office="NYC")*(C2:C16="Electronics"),Sales02))} -> 15414
A5: Aaron | B5: BOS | C5: Apparel | D5: 17347 | E5: 10990
A6: Phil | B6: NYC | C6: Electronics | D6: 19635 | E6: 10283 | G6: # of rows where 2016 Sales > 2015 Sales: | H6: {=SUM(--(Sales02>Sales01))} -> 9
A7: Tom | B7: NYC | C7: Electronics | D7: 13190 | E7: 15332
A8: Bill | B8: NYC | C8: Electronics | D8: 17585 | E8: 15414 | G8: Sum of 2015 and 2016 Sales in Boston: | H8: {=SUM((D2:D16+E2:E16)*(B2:B16="BOS"))} -> 140337
A9: Lauren | B9: NYC | C9: Apparel | D9: 19588 | E9: 21973
A10: Jason | B10: NYC | C10: Apparel | D10: 15769 | E10: 18721
A11: Mark | B11: NYC | C11: Apparel | D11: 25347 | E11: 25897
A12: Kim | B12: CHI | C12: Electronics | D12: 29120 | E12: 21824
A13: Tina | B13: CHI | C13: Electronics | D13: 19325 | E13: 26697
A14: Jean | B14: CHI | C14: Electronics | D14: 23810 | E14: 28543
A15: Sam | B15: CHI | C15: Apparel | D15: 26508 | E15: 28682
A16: Ashley | B16: CHI | C16: Apparel | D16: 17872 | E16: 17631

Sheet Bonus Array Function
A1: Original Array | F1: Criteria | I1: Sub-Array
A2: Date | B2: Campaign | C2: Revenue | D2: Spend | F2: Start Date: | G2: 42373 | I2: Start Date | J2: Campaign | K2: Revenue | L2: Spend
A3: 42370 | B3: A | C3: 25000 | D3: 8000 | F3: End Date: | G3: 42379 | I3: {=IFERROR(INDEX(A$3:A$14,SMALL(IF(($C$3:$C$14>=$G$4)*($A$3:$A$14>=$G$2)*($A$3:$A$14<=$G$3),ROW(A$3:A$14)-2),ROWS(A$3:A3))),"")} -> 42373 | J3: {=IFERROR(INDEX(B$3:B$14,SMALL(IF(($C$3:$C$14>=$G$4)*($A$3:$A$14>=$G$2)*($A$3:$A$14<=$G$3),ROW(B$3:B$14)-2),ROWS(B$3:B3))),"")} -> D | K3: {=IFERROR(INDEX(C$3:C$14,SMALL(IF(($C$3:$C$14>=$G$4)*($A$3:$A$14>=$G$2)*($A$3:$A$14<=$G$3),ROW(C$3:C$14)-2),ROWS(C$3:C3))),"")} -> 150000 | L3: {=IFERROR(INDEX(D$3:D$14,SMALL(IF(($C$3:$C$14>=$G$4)*($A$3:$A$14>=$G$2)*($A$3:$A$14<=$G$3),ROW(D$3:D$14)-2),ROWS(D$3:D3))),"")} -> 8000
A4: 42371 | B4: B | C4: 40000 | D4: 10000 | F4: Minimum Revenue: | G4: 100000 | I4: {=IFERROR(INDEX(A$3:A$14,SMALL(IF(($C$3:$C$14>=$G$4)*($A$3:$A$14>=$G$2)*($A$3:$A$14<=$G$3),ROW(A$3:A$14)-2),ROWS(A$3:A4))),"")} -> 42376 | J4: {=IFERROR(INDEX(B$3:B$14,SMALL(IF(($C$3:$C$14>=$G$4)*($A$3:$A$14>=$G$2)*($A$3:$A$14<=$G$3),ROW(B$3:B$14)-2),ROWS(B$3:B4))),"")} -> G | K4: {=IFERROR(INDEX(C$3:C$14,SMALL(IF(($C$3:$C$14>=$G$4)*($A$3:$A$14>=$G$2)*($A$3:$A$14<=$G$3),ROW(C$3:C$14)-2),ROWS(C$3:C4))),"")} -> 120000 | L4: {=IFERROR(INDEX(D$3:D$14,SMALL(IF(($C$3:$C$14>=$G$4)*($A$3:$A$14>=$G$2)*($A$3:$A$14<=$G$3),ROW(D$3:D$14)-2),ROWS(D$3:D4))),"")} -> 12000
A5: 42372 | B5: C | C5: 135000 | D5: 12500 | I5: {=IFERROR(INDEX(A$3:A$14,SMALL(IF(($C$3:$C$14>=$G$4)*($A$3:$A$14>=$G$2)*($A$3:$A$14<=$G$3),ROW(A$3:A$14)-2),ROWS(A$3:A5))),"")} -> 42377 | J5: {=IFERROR(INDEX(B$3:B$14,SMALL(IF(($C$3:$C$14>=$G$4)*($A$3:$A$14>=$G$2)*($A$3:$A$14<=$G$3),ROW(B$3:B$14)-2),ROWS(B$3:B5))),"")} -> H | K5: {=IFERROR(INDEX(C$3:C$14,SMALL(IF(($C$3:$C$14>=$G$4)*($A$3:$A$14>=$G$2)*($A$3:$A$14<=$G$3),ROW(C$3:C$14)-2),ROWS(C$3:C5))),"")} -> 105000 | L5: {=IFERROR(INDEX(D$3:D$14,SMALL(IF(($C$3:$C$14>=$G$4)*($A$3:$A$14>=$G$2)*($A$3:$A$14<=$G$3),ROW(D$3:D$14)-2),ROWS(D$3:D5))),"")} -> 10000
A6: 42373 | B6: D | C6: 150000 | D6: 8000 | I6: {=IFERROR(INDEX(A$3:A$14,SMALL(IF(($C$3:$C$14>=$G$4)*($A$3:$A$14>=$G$2)*($A$3:$A$14<=$G$3),ROW(A$3:A$14)-2),ROWS(A$3:A6))),"")} -> 42379 | J6: {=IFERROR(INDEX(B$3:B$14,SMALL(IF(($C$3:$C$14>=$G$4)*($A$3:$A$14>=$G$2)*($A$3:$A$14<=$G$3),ROW(B$3:B$14)-2),ROWS(B$3:B6))),"")} -> J | K6: {=IFERROR(INDEX(C$3:C$14,SMALL(IF(($C$3:$C$14>=$G$4)*($A$3:$A$14>=$G$2)*($A$3:$A$14<=$G$3),ROW(C$3:C$14)-2),ROWS(C$3:C6))),"")} -> 110000 | L6: {=IFERROR(INDEX(D$3:D$14,SMALL(IF(($C$3:$C$14>=$G$4)*($A$3:$A$14>=$G$2)*($A$3:$A$14<=$G$3),ROW(D$3:D$14)-2),ROWS(D$3:D6))),"")} -> 12000
A7: 42374 | B7: E | C7: 25000 | D7: 12000
A8: 42375 | B8: F | C8: 25000 | D8: 8000
A9: 42376 | B9: G | C9: 120000 | D9: 12000
A10: 42377 | B10: H | C10: 105000 | D10: 10000
A11: 42378 | B11: I | C11: 25000 | D11: 12000
A12: 42379 | B12: J | C12: 110000 | D12: 12000
A13: 42380 | B13: K | C13: 50000 | D13: 10000
A14: 42381 | B14: L | C14: 25000 | D14: 12000
I15: {=IFERROR(INDEX(A$3:A$14,SMALL(IF(($C$3:$C$14>=$G$4)*($A$3:$A$14>=$G$2)*($A$3:$A$14<=$G$3),ROW(A$3:A$14)-ROW(A$3)+1),ROWS(A$3:A15))),"")} | J15: {=IFERROR(INDEX(B$3:B$14,SMALL(IF(($C$3:$C$14>=$G$4)*($A$3:$A$14>=$G$2)*($A$3:$A$14<=$G$3),ROW(B$3:B$14)-ROW(B$3)+1),ROWS(B$3:B15))),"")} | K15: {=IFERROR(INDEX(C$3:C$14,SMALL(IF(($C$3:$C$14>=$G$4)*($A$3:$A$14>=$G$2)*($A$3:$A$14<=$G$3),ROW(C$3:C$14)-ROW(C$3)+1),ROWS(C$3:C15))),"")} | L15: {=IFERROR(INDEX(D$3:D$14,SMALL(IF(($C$3:$C$14>=$G$4)*($A$3:$A$14>=$G$2)*($A$3:$A$14<=$G$3),ROW(D$3:D$14)-ROW(D$3)+1),ROWS(D$3:D15))),"")}
I16: {=IFERROR(INDEX(A$3:A$14,SMALL(IF(($C$3:$C$14>=$G$4)*($A$3:$A$14>=$G$2)*($A$3:$A$14<=$G$3),ROW(A$3:A$14)-ROW(A$3)+1),ROWS(A$3:A16))),"")} | J16: {=IFERROR(INDEX(B$3:B$14,SMALL(IF(($C$3:$C$14>=$G$4)*($A$3:$A$14>=$G$2)*($A$3:$A$14<=$G$3),ROW(B$3:B$14)-ROW(B$3)+1),ROWS(B$3:B16))),"")} | K16: {=IFERROR(INDEX(C$3:C$14,SMALL(IF(($C$3:$C$14>=$G$4)*($A$3:$A$14>=$G$2)*($A$3:$A$14<=$G$3),ROW(C$3:C$14)-ROW(C$3)+1),ROWS(C$3:C16))),"")} | L16: {=IFERROR(INDEX(D$3:D$14,SMALL(IF(($C$3:$C$14>=$G$4)*($A$3:$A$14>=$G$2)*($A$3:$A$14<=$G$3),ROW(D$3:D$14)-ROW(D$3)+1),ROWS(D$3:D16))),"")}
I17: {=IFERROR(INDEX(A$3:A$14,SMALL(IF(($C$3:$C$14>=$G$4)*($A$3:$A$14>=$G$2)*($A$3:$A$14<=$G$3),ROW(A$3:A$14)-ROW(A$3)+1),ROWS(A$3:A17))),"")} | J17: {=IFERROR(INDEX(B$3:B$14,SMALL(IF(($C$3:$C$14>=$G$4)*($A$3:$A$14>=$G$2)*($A$3:$A$14<=$G$3),ROW(B$3:B$14)-ROW(B$3)+1),ROWS(B$3:B17))),"")} | K17: {=IFERROR(INDEX(C$3:C$14,SMALL(IF(($C$3:$C$14>=$G$4)*($A$3:$A$14>=$G$2)*($A$3:$A$14<=$G$3),ROW(C$3:C$14)-ROW(C$3)+1),ROWS(C$3:C17))),"")} | L17: {=IFERROR(INDEX(D$3:D$14,SMALL(IF(($C$3:$C$14>=$G$4)*($A$3:$A$14>=$G$2)*($A$3:$A$14<=$G$3),ROW(D$3:D$14)-ROW(D$3)+1),ROWS(D$3:D17))),"")}
I18: {=IFERROR(INDEX(A$3:A$14,SMALL(IF(($C$3:$C$14>=$G$4)*($A$3:$A$14>=$G$2)*($A$3:$A$14<=$G$3),ROW(A$3:A$14)-ROW(A$3)+1),ROWS(A$3:A18))),"")} | J18: {=IFERROR(INDEX(B$3:B$14,SMALL(IF(($C$3:$C$14>=$G$4)*($A$3:$A$14>=$G$2)*($A$3:$A$14<=$G$3),ROW(B$3:B$14)-ROW(B$3)+1),ROWS(B$3:B18))),"")} | K18: {=IFERROR(INDEX(C$3:C$14,SMALL(IF(($C$3:$C$14>=$G$4)*($A$3:$A$14>=$G$2)*($A$3:$A$14<=$G$3),ROW(C$3:C$14)-ROW(C$3)+1),ROWS(C$3:C18))),"")} | L18: {=IFERROR(INDEX(D$3:D$14,SMALL(IF(($C$3:$C$14>=$G$4)*($A$3:$A$14>=$G$2)*($A$3:$A$14<=$G$3),ROW(D$3:D$14)-ROW(D$3)+1),ROWS(D$3:D18))),"")}
I19: {=IFERROR(INDEX(A$3:A$14,SMALL(IF(($C$3:$C$14>=$G$4)*($A$3:$A$14>=$G$2)*($A$3:$A$14<=$G$3),ROW(A$3:A$14)-ROW(A$3)+1),ROWS(A$3:A19))),"")} | J19: {=IFERROR(INDEX(B$3:B$14,SMALL(IF(($C$3:$C$14>=$G$4)*($A$3:$A$14>=$G$2)*($A$3:$A$14<=$G$3),ROW(B$3:B$14)-ROW(B$3)+1),ROWS(B$3:B19))),"")} | K19: {=IFERROR(INDEX(C$3:C$14,SMALL(IF(($C$3:$C$14>=$G$4)*($A$3:$A$14>=$G$2)*($A$3:$A$14<=$G$3),ROW(C$3:C$14)-ROW(C$3)+1),ROWS(C$3:C19))),"")} | L19: {=IFERROR(INDEX(D$3:D$14,SMALL(IF(($C$3:$C$14>=$G$4)*($A$3:$A$14>=$G$2)*($A$3:$A$14<=$G$3),ROW(D$3:D$14)-ROW(D$3)+1),ROWS(D$3:D19))),"")}
